duneapi/__init__.py
duneapi/api.py
duneapi/constants.py
duneapi/dashboard.py
duneapi/file_io.py
duneapi/logger.py
duneapi/py.typed
duneapi/query_template.py
duneapi/response.py
duneapi/types.py
duneapi/util.py
duneapi-8.0.0.dist-info/LICENCE
duneapi-8.0.0.dist-info/METADATA
duneapi-8.0.0.dist-info/WHEEL
duneapi-8.0.0.dist-info/top_level.txt
duneapi-8.0.0.dist-info/RECORD
