Metadata-Version: 2.1
Name: duneapi
Version: 8.0.0
Summary: A simple framework for interacting with Dune Analytics unsupported API.
Home-page: https://github.com/bh2smith/duneapi
Author: Benjamin H. Smith
Author-email: bh2smith@gmail.com
License: Apache License Version 2.0
Project-URL: Tracker, https://github.com/bh2smith/duneapi/issues
Classifier: Programming Language :: Python :: 3
Classifier: License :: OSI Approved :: Apache Software License
Classifier: Operating System :: OS Independent
Requires-Python: >=3.9
License-File: LICENCE
Requires-Dist: requests (>=2.27.1)
Requires-Dist: types-requests (>=2.27.13)
Requires-Dist: python-dotenv (>=0.20.0)
Requires-Dist: web3 (>=5.28.0)
Requires-Dist: Deprecated (>=1.2.13)
Requires-Dist: types-Deprecated (>=1.2.9)
